gmpackages-0.1.data/scripts/gmpackages
gmpackages-0.1.data/scripts/pckg
package/__init__.py
package/my_classes.py
package/utilities.py
package/nlp/__init__.py
package/nlp/embedding.py
package/nlp/preprocessing.py
package/nlp/summarization.py
package/symspellpy/__init__.py
package/symspellpy/editdistance.py
package/symspellpy/helpers.py
package/symspellpy/symspellpy.py
gmpackages-0.1.dist-info/METADATA
gmpackages-0.1.dist-info/WHEEL
gmpackages-0.1.dist-info/top_level.txt
gmpackages-0.1.dist-info/RECORD
